README
setup.cfg
setup.py
tableaudocumentapi/__init__.py
tableaudocumentapi/connection.py
tableaudocumentapi/datasource.py
tableaudocumentapi/dbclass.py
tableaudocumentapi/field.py
tableaudocumentapi/multilookup_dict.py
tableaudocumentapi/workbook.py
tableaudocumentapi/xfile.py
test/test_datasource.py
test/test_field.py
test/test_multidict.py
test/test_workbook.py
test/test_xfile.py
testtableaudocumentapi.egg-info/PKG-INFO
testtableaudocumentapi.egg-info/SOURCES.txt
testtableaudocumentapi.egg-info/dependency_links.txt
testtableaudocumentapi.egg-info/top_level.txt