Metadata-Version: 1.0
Name: testtableaudocumentapi
Version: 0.0.3
Summary: A Python module for working with Tableau files.
Home-page: UNKNOWN
Author: Avijit
Author-email: github@tableau.com
License: MIT
Platform: UNKNOWN
